LICENSE
MANIFEST.in
README.md
setup.py
qrovkbwaun/__init__.py
qrovkbwaun/api_helper.py
qrovkbwaun/configuration.py
qrovkbwaun/decorators.py
qrovkbwaun/qrovkbwaun_client.py
qrovkbwaun.egg-info/PKG-INFO
qrovkbwaun.egg-info/SOURCES.txt
qrovkbwaun.egg-info/dependency_links.txt
qrovkbwaun.egg-info/requires.txt
qrovkbwaun.egg-info/top_level.txt
qrovkbwaun/controllers/__init__.py
qrovkbwaun/controllers/api_controller.py
qrovkbwaun/controllers/base_controller.py
qrovkbwaun/exceptions/__init__.py
qrovkbwaun/exceptions/api_exception.py
qrovkbwaun/http/__init__.py
qrovkbwaun/http/http_call_back.py
qrovkbwaun/http/http_client.py
qrovkbwaun/http/http_context.py
qrovkbwaun/http/http_method_enum.py
qrovkbwaun/http/http_request.py
qrovkbwaun/http/http_response.py
qrovkbwaun/http/requests_client.py
qrovkbwaun/http/auth/__init__.py
qrovkbwaun/http/auth/basic_auth.py
qrovkbwaun/models/__init__.py
qrovkbwaun/models/suite_code_enum.py
tests/__init__.py
tests/http_response_catcher.py
tests/test_helper.py
tests/controllers/__init__.py
tests/controllers/controller_test_base.py
tests/controllers/test_api_controller.py